pyloggrid/__init__.py
pyloggrid/Libs/IOLib.py
pyloggrid/Libs/__init__.py
pyloggrid/Libs/custom_logger.py
pyloggrid/Libs/datasci.py
pyloggrid/Libs/misc.py
pyloggrid/Libs/plotLib.py
pyloggrid/Libs/singlethread_numpy.py
pyloggrid/LogGrid/DataExplorer.py
pyloggrid/LogGrid/Framework.py
pyloggrid/LogGrid/Grid.py
pyloggrid/LogGrid/Makefile
pyloggrid/LogGrid/Makefile.windows
pyloggrid/LogGrid/__init__.py
pyloggrid/LogGrid/compute_convolution_kernel.cpython-313-x86_64-linux-gnu.so
pyloggrid/LogGrid/compute_convolution_kernel.pyx
pyloggrid/LogGrid/convolver_c.c
pyloggrid/LogGrid/convolver_c.so
pyloggrid/LogGrid/setup_linux.py
pyloggrid/LogGrid/setup_windows.py
pyloggrid-2.5.1.dist-info/METADATA
pyloggrid-2.5.1.dist-info/WHEEL
pyloggrid-2.5.1.dist-info/licenses/LICENSE
pyloggrid-2.5.1.dist-info/RECORD
