Metadata-Version: 2.4
Name: pyloggrid
Version: 2.5.1
Summary: A python library to perform simulations on logarithmic lattices
Author-email: Amaury Barral <amaury.barral@protonmail.com>
License:                     GNU GENERAL PUBLIC LICENSE
License-File: LICENSE
Requires-Python: <3.14,>=3.9
Requires-Dist: cython>=3.0.4
Requires-Dist: h5py>=3.8.0
Requires-Dist: imageio-ffmpeg>=0.4.8
Requires-Dist: imageio>=2.28.1
Requires-Dist: joblib>=1.2.0
Requires-Dist: matplotlib>=3.8.0
Requires-Dist: numpy>=1.26.1
Requires-Dist: orjson>=3.8.11
Requires-Dist: pyqt6>=6.5.3
Requires-Dist: rkstiff>=0.3.0
Requires-Dist: scienceplots>=2.0.1
Requires-Dist: scipy>=1.11.2
